llamatry/__init__.py
llamatry/openai.py
llamatry/trace.py
llamatry-0.1.9.dist-info/METADATA
llamatry-0.1.9.dist-info/WHEEL
llamatry-0.1.9.dist-info/RECORD
