Metadata-Version: 2.1
Name: llamatry
Version: 0.1.9
Summary: opentelemetry instrumentation for openai's completions api
Home-page: https://github.com/jxnl/llamatry
Author: Jason
Author-email: jason@jxnl.co
Requires-Python: >=3.9,<4.0
Classifier: Programming Language :: Python :: 3
Classifier: Programming Language :: Python :: 3.9
Classifier: Programming Language :: Python :: 3.10
Classifier: Programming Language :: Python :: 3.11
Requires-Dist: openai (>=0.27.6,<0.28.0)
Requires-Dist: opentelemetry-api (>=1.17.0,<2.0.0)
Requires-Dist: opentelemetry-instrumentation (>=0.38b0,<0.39)
Requires-Dist: opentelemetry-instrumentation-requests (>=0.38b0,<0.39)
Requires-Dist: opentelemetry-sdk (>=1.17.0,<2.0.0)
Requires-Dist: urllib3 (<2.0)
Project-URL: Repository, https://github.com/jxnl/llamatry
